flylogging/__init__.py
flylogging/context_logger.py
flylogging/handler_handler.py
flylogging/json_formatter.py
flylogging-0.0.2a3.dist-info/METADATA
flylogging-0.0.2a3.dist-info/WHEEL
flylogging-0.0.2a3.dist-info/top_level.txt
flylogging-0.0.2a3.dist-info/RECORD
